bagua_cuda111-0.9.0.data/scripts/bagua_install_deps.py
bagua_cuda111-0.9.0.data/scripts/bagua_sys_perf
bagua_core/__init__.py
bagua_core/bagua_install_deps.py
bagua_core/bagua_core.cpython-37m-x86_64-linux-gnu.so
bagua_core/_environment.py
bagua_core/.data/bagua-net/libnccl-net.so
tests/__init__.py
tests/test_bagua_define.py
tests/internal/__init__.py
tests/internal/compressor.py
tests/internal/common_utils.py
tests/internal/multi_process.py
bagua/bagua_define.py
bagua/__init__.py
bagua/version.py
bagua/torch_api/communication.py
bagua/torch_api/tensor.py
bagua/torch_api/__init__.py
bagua/torch_api/utils.py
bagua/torch_api/env.py
bagua/torch_api/bucket.py
bagua/torch_api/distributed.py
bagua/torch_api/model_parallel/__init__.py
bagua/torch_api/model_parallel/moe/__init__.py
bagua/torch_api/model_parallel/moe/experts.py
bagua/torch_api/model_parallel/moe/sharded_moe.py
bagua/torch_api/model_parallel/moe/utils.py
bagua/torch_api/model_parallel/moe/layer.py
bagua/torch_api/contrib/load_balancing_data_loader.py
bagua/torch_api/contrib/cached_dataset.py
bagua/torch_api/contrib/cache_loader.py
bagua/torch_api/contrib/__init__.py
bagua/torch_api/contrib/sync_batchnorm.py
bagua/torch_api/contrib/fuse/__init__.py
bagua/torch_api/contrib/fuse/optimizer.py
bagua/torch_api/contrib/utils/store.py
bagua/torch_api/contrib/utils/__init__.py
bagua/torch_api/contrib/utils/redis_store.py
bagua/torch_api/data_parallel/__init__.py
bagua/torch_api/data_parallel/functional.py
bagua/torch_api/data_parallel/bagua_distributed.py
bagua/torch_api/data_parallel/distributed.py
bagua/torch_api/algorithms/gradient_allreduce.py
bagua/torch_api/algorithms/async_model_average.py
bagua/torch_api/algorithms/__init__.py
bagua/torch_api/algorithms/decentralized.py
bagua/torch_api/algorithms/base.py
bagua/torch_api/algorithms/q_adam.py
bagua/torch_api/algorithms/bytegrad.py
bagua/torch_api/checkpoint/__init__.py
bagua_cuda111-0.9.0.dist-info/entry_points.txt
bagua_cuda111-0.9.0.dist-info/RECORD
bagua_cuda111-0.9.0.dist-info/top_level.txt
bagua_cuda111-0.9.0.dist-info/METADATA
bagua_cuda111-0.9.0.dist-info/WHEEL
bagua_cuda111-0.9.0.dist-info/LICENSE
